sensorrelay/__init__.py
sensorrelay/sensorrelay.py
sensorrelay-0.2.dist-info/DESCRIPTION.rst
sensorrelay-0.2.dist-info/METADATA
sensorrelay-0.2.dist-info/RECORD
sensorrelay-0.2.dist-info/WHEEL
sensorrelay-0.2.dist-info/metadata.json
sensorrelay-0.2.dist-info/top_level.txt
