Metadata-Version: 2.0
Name: sensorrelay
Version: 0.2
Summary: Python module for sending and receiving messages to/from a
Home-page: http://www.dis.cwi.nl
Author: Thomas Röggla
Author-email: t.roggla@cwi.nl
License: BSD 2-clause
Keywords: publish subscribe websocket
Platform: UNKNOWN
Requires-Dist: websocket-client (>=0.30.0)
